nanonis_tramea_specs/NanonisClass.py
nanonis_tramea_specs/__init__.py
nanonis_tramea_specs/test.py
nanonis_tramea_specs-0.0.5.dist-info/METADATA
nanonis_tramea_specs-0.0.5.dist-info/WHEEL
nanonis_tramea_specs-0.0.5.dist-info/licenses/LICENSE.txt
nanonis_tramea_specs-0.0.5.dist-info/RECORD
